pollination_dash_viewer/MyComponent.py
pollination_dash_viewer/VTKDashViewer.py
pollination_dash_viewer/__init__.py
pollination_dash_viewer/_imports_.py
pollination_dash_viewer/metadata.json
pollination_dash_viewer/package-info.json
pollination_dash_viewer/pollination_dash_viewer.js
pollination_dash_viewer/pollination_dash_viewer.js.LICENSE.txt
pollination_dash_viewer-1.1.0.dist-info/LICENSE
pollination_dash_viewer-1.1.0.dist-info/METADATA
pollination_dash_viewer-1.1.0.dist-info/WHEEL
pollination_dash_viewer-1.1.0.dist-info/top_level.txt
pollination_dash_viewer-1.1.0.dist-info/RECORD
